sequence_detector.v
module sequence_detector( 
    input clk, rst, 
    input sequence_in, 
    output reg sequence_out
); 

parameter S0 = 0, S1 = 1, S2 = 2, S3 = 3, S4 = 4, S5 = 5; 

reg [2:0] state, next_state;

always @(posedge clk or posedge rst) begin 
    if (rst) 
        state <= S0; 
    else 
        state <= next_state; 
end

// 11010
always @(*) begin 
    case (state) 

        S0 : begin 
            if (sequence_in) 
                next_state = S1; 
            else 
                next_state = S0; 

            sequence_out = 0;
        end 

        S1 : begin 
            if (sequence_in) 
                next_state = S2; 
            else
                next_state = S0; 

            sequence_out = 0;
        end 

        S2 : begin 
            if (sequence_in)
                next_state = S2; 
            else 
                next_state = S3;

            sequence_out = 0;  
        end 

        S3 : begin 
            if (sequence_in)
                next_state = S4; 
            else 
                next_state = S0; 

            sequence_out = 0;
        end 

        S4 : begin  
            if (sequence_in)
                next_state = S2; 
            else 
                next_state = S5; 

            sequence_out = 0; 
        end

        S5 : begin 
            if (sequence_in)
                next_state = S1; 
            else 
                next_state = S0; 

            sequence_out = 1; 
        end
        
        default : begin 
            next_state = S0; 
            sequence_out = 0; 
        end 

    endcase 
end 

endmodule

sequence_detector_tb.v
module sequence_detector_tb();

reg clk; 
reg rst; 
reg sequence_in; 
wire sequence_out; 

sequence_detector DUT( 
    .clk(clk),
    .rst(rst),
    .sequence_in(sequence_in),
    .sequence_out(sequence_out)
);

always #5 clk = ~clk; 

initial begin
    clk=0; 
    rst=1; 
    sequence_in=0;

    #10; 

    rst = 0;
    
    //hacemos la prueba con la secuencia solicitada 11010
    sequence_in= 1; 
    #10; 
    sequence_in= 1; 
    #10; 
    sequence_in=0; 
    #10; 
    sequence_in=1; 
    #10; 
    sequence_in=0;
    #10;

    $finish;
end


initial begin 
    $monitor("rst=%b | sequence_in=%b | sequence_out=%b",rst,sequence_in,sequence_out); 
end 

 initial begin
        $dumpfile("sequence_detector_tb.vcd");
        $dumpvars(0, sequence_detector_tb);
    end

endmodule

sequence_detector_tb.vcd
$date
	Sat Jun 13 10:32:19 2026
$end
$version
	Icarus Verilog
$end
$timescale
	1s
$end
$scope module sequence_detector_tb $end
$var wire 1 ! sequence_out $end
$var reg 1 " clk $end
$var reg 1 # rst $end
$var reg 1 $ sequence_in $end
$scope module DUT $end
$var wire 1 " clk $end
$var wire 1 # rst $end
$var wire 1 $ sequence_in $end
$var parameter 32 % S0 $end
$var parameter 32 & S1 $end
$var parameter 32 ' S2 $end
$var parameter 32 ( S3 $end
$var parameter 32 ) S4 $end
$var parameter 32 * S5 $end
$var reg 3 + next_state [2:0] $end
$var reg 1 ! sequence_out $end
$var reg 3 , state [2:0] $end
$upscope $end
$upscope $end
$enddefinitions $end
$comment Show the parameter values. $end
$dumpall
b101 *
b100 )
b11 (
b10 '
b1 &
b0 %
$end
#0
$dumpvars
b0 ,
b0 +
0$
1#
0"
0!
$end
#5
1"
#10
b1 +
0"
1$
0#
#15
b10 +
b1 ,
1"
#20
0"
#25
b10 ,
1"
#30
b11 +
0"
0$
#35
b0 +
b11 ,
1"
#40
b100 +
0"
1$
#45
b10 +
b100 ,
1"
#50
b101 +
0"
0$
#55
1!
b0 +
b101 ,
1"
